[{"label":"Alpine","value":"ALP","people_h":4839,"people_w":2420},{"label":"Alta","value":"ALA","people_h":117,"people_w":1724},{"label":"American Fork","value":"AFK","people_h":15994,"people_w":25624},{"label":"Bluffdale","value":"BDL","people_h":8744,"people_w":5803},{"label":"Bountiful","value":"BNT","people_h":20714,"people_w":12336},{"label":"Box Elder County","value":"z03","people_h":14821,"people_w":10096},{"label":"Brigham City","value":"BGM","people_h":10638,"people_w":8582},{"label":"Brighton","value":"BRT","people_h":213,"people_w":1508},{"label":"Cedar Fort","value":"CDF","people_h":227,"people_w":92},{"label":"Cedar Hills","value":"CHL","people_h":4845,"people_w":1037},{"label":"Centerville","value":"CEN","people_h":7681,"people_w":6772},{"label":"Charleston","value":"CHA","people_h":254,"people_w":218},{"label":"Clearfield","value":"CLF","people_h":14257,"people_w":16373},{"label":"Clinton","value":"CLI","people_h":11030,"people_w":3058},{"label":"Coalville","value":"COA","people_h":810,"people_w":685},{"label":"Copperton","value":"CMT","people_h":430,"people_w":89},{"label":"Cottonwood Heights","value":"CWH","people_h":17497,"people_w":20526},{"label":"Daniel","value":"DAN","people_h":834,"people_w":347},{"label":"Davis County","value":"z11","people_h":162567,"people_w":121491},{"label":"Draper","value":"DRA","people_h":24321,"people_w":47665},{"label":"Eagle Mountain","value":"EAG","people_h":21231,"people_w":4557},{"label":"Elk Ridge","value":"ELK","people_h":2224,"people_w":306},{"label":"Emigration Canyon","value":"EMT","people_h":765,"people_w":114},{"label":"Fairfield","value":"FFD","people_h":68,"people_w":111},{"label":"Farmington","value":"FAR","people_h":10730,"people_w":11586},{"label":"Farr West","value":"FRR","people_h":4010,"people_w":3895},{"label":"Francis","value":"FCS","people_h":671,"people_w":136},{"label":"Fruit Heights","value":"FTH","people_h":2644,"people_w":596},{"label":"Genola","value":"GLA","people_h":735,"people_w":290},{"label":"Goshen","value":"GOS","people_h":424,"people_w":67},{"label":"Grantsville","value":"GRL","people_h":6786,"people_w":2486},{"label":"Harrisville","value":"HAR","people_h":3602,"people_w":1676},{"label":"Heber City","value":"HEB","people_h":9772,"people_w":6856},{"label":"Henefer","value":"HNF","people_h":409,"people_w":83},{"label":"Herriman","value":"HER","people_h":28511,"people_w":6835},{"label":"Highland","value":"HGH","people_h":9813,"people_w":3512},{"label":"Holladay","value":"HOL","people_h":15143,"people_w":11301},{"label":"Hooper","value":"HOO","people_h":4325,"people_w":657},{"label":"Huntsville","value":"HVL","people_h":269,"people_w":105},{"label":"Independence","value":"IND","people_h":72,"people_w":5},{"label":"Interlaken","value":"INT","people_h":80,"people_w":8},{"label":"Kamas","value":"KMS","people_h":1138,"people_w":1428},{"label":"Kaysville","value":"KAY","people_h":13912,"people_w":9022},{"label":"Kearns","value":"KMT","people_h":18682,"people_w":3892},{"label":"Layton","value":"LAY","people_h":36266,"people_w":29825},{"label":"Lehi","value":"LEH","people_h":39091,"people_w":47477},{"label":"Lindon","value":"LIN","people_h":5538,"people_w":16100},{"label":"Magna","value":"MMT","people_h":14832,"people_w":7300},{"label":"Mapleton","value":"MAP","people_h":5653,"people_w":2497},{"label":"Marriott-Slaterville","value":"MSL","people_h":1130,"people_w":1916},{"label":"Midvale","value":"MID","people_h":18523,"people_w":21517},{"label":"Midway","value":"MWY","people_h":2960,"people_w":1529},{"label":"Millcreek","value":"MLC","people_h":32277,"people_w":25758},{"label":"Morgan","value":"MRG","people_h":2036,"people_w":1369},{"label":"Morgan County","value":"z29","people_h":2036,"people_w":1369},{"label":"Murray","value":"MUR","people_h":26968,"people_w":45608},{"label":"North Ogden","value":"NOG","people_h":10130,"people_w":3205},{"label":"North Salt Lake","value":"NSL","people_h":10504,"people_w":15308},{"label":"Oakley","value":"OKL","people_h":698,"people_w":322},{"label":"Ogden","value":"OGD","people_h":41369,"people_w":61255},{"label":"Orem","value":"ORM","people_h":45797,"people_w":49327},{"label":"Park City","value":"PRK","people_h":4639,"people_w":13690},{"label":"Payson","value":"PAY","people_h":11428,"people_w":7266},{"label":"Perry","value":"PRY","people_h":2931,"people_w":1296},{"label":"Plain City","value":"PLN","people_h":4134,"people_w":1136},{"label":"Pleasant Grove","value":"PGR","people_h":18134,"people_w":16003},{"label":"Pleasant View","value":"PVW","people_h":5012,"people_w":2491},{"label":"Provo","value":"PVO","people_h":43066,"people_w":60778},{"label":"Riverdale","value":"RVD","people_h":4321,"people_w":7674},{"label":"Riverton","value":"RVT","people_h":23983,"people_w":12462},{"label":"Roy","value":"ROY","people_h":19396,"people_w":9141},{"label":"Salem","value":"SLM","people_h":4970,"people_w":2251},{"label":"Salt Lake City","value":"SLC","people_h":96823,"people_w":281202},{"label":"Salt Lake County","value":"z35","people_h":594351,"people_w":738579},{"label":"Sandy","value":"SAN","people_h":48728,"people_w":50924},{"label":"Santaquin","value":"SAQ","people_h":7212,"people_w":1556},{"label":"Saratoga Springs","value":"SAR","people_h":18554,"people_w":5234},{"label":"South Jordan","value":"SJC","people_h":39688,"people_w":35308},{"label":"South Ogden","value":"SOG","people_h":7886,"people_w":7959},{"label":"South Salt Lake","value":"SSL","people_h":12919,"people_w":33112},{"label":"South Weber","value":"SWE","people_h":3482,"people_w":937},{"label":"Spanish Fork","value":"SFK","people_h":23586,"people_w":15337},{"label":"Springville","value":"SPV","people_h":17603,"people_w":14461},{"label":"Summit County","value":"z43","people_h":8365,"people_w":16344},{"label":"Sunset","value":"SUN","people_h":2663,"people_w":1329},{"label":"Syracuse","value":"SYR","people_h":14981,"people_w":4772},{"label":"Taylorsville","value":"TAY","people_h":31055,"people_w":20109},{"label":"Tooele","value":"TOO","people_h":20617,"people_w":10072},{"label":"Tooele County","value":"z45","people_h":27403,"people_w":12558},{"label":"Uintah","value":"UIN","people_h":623,"people_w":315},{"label":"Utah County","value":"z49","people_h":307938,"people_w":278642},{"label":"Vineyard","value":"VIN","people_h":6200,"people_w":2151},{"label":"Wallsburg","value":"WBG","people_h":161,"people_w":137},{"label":"Wasatch County","value":"z51","people_h":14133,"people_w":9100},{"label":"Washington Terrace","value":"WAT","people_h":4407,"people_w":3871},{"label":"Weber County","value":"z57","people_h":119355,"people_w":109841},{"label":"West Bountiful","value":"WEB","people_h":2793,"people_w":2434},{"label":"West Haven","value":"WHV","people_h":8741,"people_w":4545},{"label":"West Jordan","value":"WJC","people_h":64598,"people_w":38041},{"label":"West Point","value":"WPT","people_h":5137,"people_w":1230},{"label":"West Valley City","value":"WVC","people_h":66604,"people_w":67356},{"label":"White City","value":"WHT","people_h":2930,"people_w":425},{"label":"Willard","value":"WIL","people_h":1252,"people_w":218},{"label":"Woodland Hills","value":"WDL","people_h":706,"people_w":188},{"label":"Woods Cross","value":"WXC","people_h":5773,"people_w":5913},{"label":null,"value":"HDT","people_h":437,"people_w":43}]